{"version":"2.0.0","contributors":["TheAncientOwl"],"title":"Run Away To Mars","artists":["TALK"],"type":["acoustic"],"notes":[],"capo":2,"chordIDs":["G","D/F#","Em7","Cadd9","Am7","D","Dsus4"],"strumms":[["D","-","D","-","D","U","D","U"],["D","-","D"],["D","U","D","U"],["D"]],"sections":{"i":{"name":"intro","type":"chords","times":1,"chunks":[{"times":1,"items":[["0 G 2 D/F# 2 Em7 2 Cadd9 2"]]}]},"v":{"name":"verse","type":"chords","times":2,"chunks":[{"times":1,"items":[["0 G 2 D/F# 2 Em7 2 Cadd9 2"]]}]},"pr":{"name":"prechorus","type":"chords","times":1,"chunks":[{"times":1,"items":[["0 Am7 2 D 2"]]}]},"c":{"name":"chorus","type":"chords","times":4,"chunks":[{"times":1,"items":[["0 Em 2 C 2 G 1"],["1 G 1","2 D/F# 2"]]}]},"b":{"name":"bridge","type":"chords","times":2,"chunks":[{"times":1,"items":[["0 Am7 2 Dsus4 2 D 2"]]}]},"o":{"name":"outro","type":"chords","times":3,"chunks":[{"times":1,"items":[["3 Em 1 C 1 G 1","3 D/F# 1 Em 1 C 1 G 1"]]}]}},"order":["i","v","pr","c","v","pr","c","b","o"],"lyrics":true,"res":[{"alias":"Run Away to Mars by TALK - Beginner Guitar Lesson & Play Along","author":"Mechanics Of Music","link":"https://youtu.be/tagR628ZDMY"},{"alias":"Run Away To Mars by Talk Guitar Tutorial Lesson!","author":"Chevans Music ~ YouTube","link":"https://youtu.be/q23IKunA78g"}]}
